claude_openrouter_tool/__init__.py
claude_openrouter_tool/main.py
claude_openrouter_tool/py.typed
claude_openrouter_tool-0.2.1.dist-info/METADATA
claude_openrouter_tool-0.2.1.dist-info/WHEEL
claude_openrouter_tool-0.2.1.dist-info/entry_points.txt
claude_openrouter_tool-0.2.1.dist-info/top_level.txt
claude_openrouter_tool-0.2.1.dist-info/RECORD
