Metadata-Version: 2.4
Name: claude-openrouter-tool
Version: 0.2.1
Summary: A tool to manage OpenRouter integration with Claude Code.
Author-email: Andrei Beliak <andrei.beliak@yahoo.com>
Maintainer-email: Andrei Beliak <andrei.beliak@yahoo.com>
License-Expression: MIT
Project-URL: Homepage, https://github.com/belyak/claude-open-router-tool
Project-URL: Repository, https://github.com/belyak/claude-open-router-tool
Project-URL: Documentation, https://github.com/belyak/claude-open-router-tool#readme
Project-URL: Issues, https://github.com/belyak/claude-open-router-tool/issues
Keywords: openrouter,claude,ai,llm,cli
Classifier: Development Status :: 4 - Beta
Classifier: Intended Audience :: Developers
Classifier: Operating System :: OS Independent
Classifier: Programming Language :: Python :: 3
Classifier: Programming Language :: Python :: 3.9
Classifier: Programming Language :: Python :: 3.10
Classifier: Programming Language :: Python :: 3.11
Classifier: Programming Language :: Python :: 3.12
Classifier: Topic :: Software Development
Classifier: Topic :: Utilities
Requires-Python: >=3.9
Requires-Dist: click>=8.0.0
Requires-Dist: requests>=2.31.0
Requires-Dist: inquirer>=3.1.3
Provides-Extra: dev
Requires-Dist: pytest>=7.4.3; extra == "dev"
Requires-Dist: pre-commit>=3.5.0; extra == "dev"
Requires-Dist: black>=23.11.0; extra == "dev"
Requires-Dist: isort>=5.12.0; extra == "dev"
Requires-Dist: ruff>=0.1.6; extra == "dev"
Requires-Dist: mypy>=1.7.0; extra == "dev"
Requires-Dist: types-click; extra == "dev"
Requires-Dist: click-plugins; extra == "dev"
Requires-Dist: mypy-extensions; extra == "dev"
Requires-Dist: pexpect>=4.8.0; extra == "dev"
Requires-Dist: types-requests>=2.31.0; extra == "dev"
